refseq_masher/__init__.py
refseq_masher/cli.py
refseq_masher/const.py
refseq_masher/taxonomy.py
refseq_masher/utils.py
refseq_masher/writers.py
refseq_masher/data/RefSeqSketches.msh
refseq_masher/data/ncbi_refseq_taxonomy_summary.csv
refseq_masher/mash/__init__.py
refseq_masher/mash/dist.py
refseq_masher/mash/parser.py
refseq_masher/mash/screen.py
refseq_masher/mash/sketch.py
refseq_masher-0.1.2.dist-info/LICENSE
refseq_masher-0.1.2.dist-info/METADATA
refseq_masher-0.1.2.dist-info/NOTICE
refseq_masher-0.1.2.dist-info/WHEEL
refseq_masher-0.1.2.dist-info/entry_points.txt
refseq_masher-0.1.2.dist-info/top_level.txt
refseq_masher-0.1.2.dist-info/RECORD
