Metadata-Version: 2.1
Name: refseq-masher
Version: 0.1.2
Summary: Mash MinHash search your sequences against a NCBI RefSeq genomes database
Home-page: https://github.com/phac-nml/refseq_masher
Author: Peter Kruczkiewicz
Author-email: peter.kruczkiewicz@gmail.com
License: Apache v2.0
Keywords: Mash MinHash RefSeq Taxonomic Classification Containment Sequencing
Platform: UNKNOWN
Classifier: Development Status :: 3 - Alpha
Classifier: Environment :: Console
Classifier: License :: OSI Approved :: GNU General Public License v3 or later (GPLv3+)
Classifier: Intended Audience :: Science/Research
Classifier: Topic :: Scientific/Engineering
Classifier: Topic :: Scientific/Engineering :: Bio-Informatics
Classifier: Programming Language :: Python :: 3.5
Classifier: Programming Language :: Python :: 3.6
Classifier: Programming Language :: Python :: Implementation :: CPython
Classifier: Operating System :: POSIX :: Linux
Requires-Dist: numpy (>=1.12.1)
Requires-Dist: pandas (>=0.20.1)
Requires-Dist: click
Provides-Extra: test
Requires-Dist: pytest (>=3.0.7) ; extra == 'test'
